sparsely/__init__.py
sparsely/base.py
sparsely/classifier.py
sparsely/regressor.py
sparsely/tune.py
sparsely-1.1.0.dist-info/LICENSE
sparsely-1.1.0.dist-info/METADATA
sparsely-1.1.0.dist-info/WHEEL
sparsely-1.1.0.dist-info/top_level.txt
sparsely-1.1.0.dist-info/RECORD
