Metadata-Version: 2.1
Name: sparsely
Version: 1.1.0
Summary: Scalable sparse linear models in Python
Author-email: Joshua Ivanhoe <joshua.k.ivanhoe@gmail.com>
License: MIT License
Project-URL: Homepage, https://github.com/joshivanhoe/sparsely
Project-URL: Issues, https://github.com/joshivanhoe/sparsely/issues
Classifier: Programming Language :: Python :: 3
Classifier: License :: OSI Approved :: MIT License
Classifier: Operating System :: OS Independent
Requires-Python: <3.12,>=3.9
License-File: LICENSE
Requires-Dist: halfspace-optimizer >=0.1.0
Requires-Dist: scikit-learn >=1.3.2
Requires-Dist: pre-commit >=3.6.0
Requires-Dist: pytest >=7.4.4
Requires-Dist: pytest-cov >=4.1.0
Requires-Dist: tomli >=2.0.1
Requires-Dist: tqdm >=4.66.1
